{
  "id": "ai-x:2076282048965206363",
  "capture_type": "post",
  "url": "https://x.com/Redknight8811/status/2076282048965206363",
  "canonical_url": "https://x.com/Redknight8811/status/2076282048965206363",
  "title": "$KLIC From a 50% Top-Line Beat to a $310M Guidance Spike: Inside the Moat of Kulicke & Soffa We talk non-stop about AI software and GPU designers, but we are completely ignoring...",
  "source_domain": "x.com",
  "author": "Redknight8811",
  "published_at": "Sun Jul 12 12:26:30 +0000 2026",
  "captured_at": "2026-07-12T13:30:01.303477+00:00",
  "storage_date": "2026-07-12",
  "content_hash": "786a4b8b65b37981893d30462f8b85d8ce004c5d3f238b9a0937ce6ef965b6f8",
  "tags": [
    "ai-x-discovery",
    "advanced_packaging",
    "risk_warning",
    "Advanced Packaging"
  ],
  "priority": "urgent",
  "research_intent": "验证 AI 基建与半导体产业链信号",
  "user_notes": "来源: ai-x-discovery；机器初筛，仍需外部核查。",
  "dedup_status": "unique",
  "duplicate_of": null,
  "status": "raw_captured",
  "paths": {
    "markdown": "/srv/cloud-vault/inbox/browser-capture/2026-07-12/aix_2076282048965206363.md",
    "json": "/srv/cloud-vault/inbox/browser-capture/2026-07-12/aix_2076282048965206363.json",
    "raw_html": null,
    "analysis_prompt": "/srv/cloud-vault/inbox/browser-capture/2026-07-12/aix_2076282048965206363.analysis_prompt.md"
  },
  "ai_x": {
    "level": "S",
    "signal_type": "risk_warning",
    "query_group": "advanced_packaging",
    "chains": [
      "Advanced Packaging"
    ],
    "investment_interpretation": "This is a watchlist signal for AI hardware supply-chain research, not a trade instruction.",
    "confidence": "medium_high",
    "verification_needed": [
      "verify source, customer relationship, timing, and supply-chain economics"
    ]
  }
}
